intest/__init__.py
intest/decorators.py
intest/runner.py
intest-0.2.0.dist-info/METADATA
intest-0.2.0.dist-info/WHEEL
intest-0.2.0.dist-info/entry_points.txt
intest-0.2.0.dist-info/licenses/LICENSE
intest-0.2.0.dist-info/RECORD
