Metadata-Version: 2.4
Name: intest
Version: 0.2.0
Summary: rust-style test macros
License-Expression: MIT
License-File: LICENSE
Requires-Python: >=3.9
